featurelab/__init__.py
featurelab/__main__.py
featurelab/categorical_processor.py
featurelab/duplicate_handler.py
featurelab/feature_extractor.py
featurelab/feature_selector.py
featurelab/null_handler.py
featurelab/outlier_detector.py
featurelab/stats_advisor.py
featurelab/utils.py
featurelab/visualizer.py
featurelab-0.1.3.dist-info/METADATA
featurelab-0.1.3.dist-info/WHEEL
featurelab-0.1.3.dist-info/entry_points.txt
featurelab-0.1.3.dist-info/top_level.txt
featurelab-0.1.3.dist-info/RECORD
