Metadata-Version: 2.4
Name: featurelab
Version: 0.1.3
Summary: Comprehensive feature engineering package with statistical guidance
Author: Shekhar Suman
Author-email: s.sumanpathak513@gmail.com
Keywords: feature-engineering data-preprocessing machine-learning pandas visualization
Classifier: Programming Language :: Python :: 3
Classifier: License :: OSI Approved :: MIT License
Classifier: Operating System :: OS Independent
Classifier: Intended Audience :: Developers
Classifier: Intended Audience :: Science/Research
Classifier: Topic :: Software Development :: Libraries
Classifier: Topic :: Scientific/Engineering :: Information Analysis
Requires-Python: >=3.7
Dynamic: author
Dynamic: author-email
Dynamic: classifier
Dynamic: description
Dynamic: description-content-type
Dynamic: keywords
Dynamic: requires-python
Dynamic: summary
